madalin_first_project/__init__.py
madalin_first_project-0.1.0.dist-info/METADATA
madalin_first_project-0.1.0.dist-info/WHEEL
madalin_first_project-0.1.0.dist-info/top_level.txt
madalin_first_project-0.1.0.dist-info/RECORD
