Metadata-Version: 2.1
Name: madalin-first-project
Version: 0.1.0
Summary: canta sub clar de lună
Author: Madalin
Author-email: lalala@yahoo.com
License: UNKNOWN
Platform: UNKNOWN
Requires-Dist: dinosay
